RLOHE/Enocder.py
RLOHE/RareLabelOneHotEncoder.py
RLOHE/TopLabeledEntries.py
RLOHE/__init__.py
RLOHE-0.0.1.dist-info/LICENSE
RLOHE-0.0.1.dist-info/METADATA
RLOHE-0.0.1.dist-info/WHEEL
RLOHE-0.0.1.dist-info/top_level.txt
RLOHE-0.0.1.dist-info/RECORD
