Metadata-Version: 2.1
Name: RLOHE
Version: 0.0.1
Summary: Rare-Label-One-Hot Encoder with Threshold Implementation and Python Package.
Home-page: https://github.com/rahulbordoloi/Rare-Label-One-Hot-Enocder
Author: Rahul Bordoloi
Author-email: rahulbordoloi24@gmail.com
License: UNKNOWN
Platform: UNKNOWN
Classifier: Programming Language :: Python :: 3.5
Classifier: Programming Language :: Python :: 3.6
Classifier: Programming Language :: Python :: 3.7
Classifier: Programming Language :: Python :: 3.8
Classifier: Programming Language :: Python :: 3.9
Classifier: Operating System :: OS Independent
Classifier: License :: OSI Approved :: GNU General Public License v3 (GPLv3)
Classifier: Topic :: Utilities
Classifier: Topic :: Scientific/Engineering
Classifier: Topic :: Software Development :: Libraries :: Python Modules
Classifier: Natural Language :: English
Classifier: Development Status :: 5 - Production/Stable
Classifier: Intended Audience :: Customer Service
Classifier: Intended Audience :: Developers
Classifier: Intended Audience :: End Users/Desktop
Requires-Dist: pandas (>=0.5)
Provides-Extra: dev
Requires-Dist: pytest (>=3.7) ; extra == 'dev'
